[
  {
    "id": "APT",
    "name": "The Apocalyptic Trilogy",
    "description": "The Apocalyptic Trilogy.",
    "levels": [3979721, 10565740, 25610878],
    "tier": "copper"
  },
  {
    "id": "Krmal1",
    "name": "KrmaL Pack I",
    "description": "A collection of challenging levels created by KrmaL.",
    "levels": [24301797, 20321297, 17711004],
    "tier": "copper"
  },
  {
    "id": "Lazerblitz",
    "name": "Lazerblitz Pack",
    "description": "Levels made by Lazerblitz.",
    "levels": [51791710, 35448603, 21952243],
    "tier": "silver"
  },
  {
    "id": "Jon",
    "name": "JonathanGD Pack",
    "description": "Levels made by JonathanGD.",
    "levels": [45239692, 69010770, 57433866],
    "tier": "silver"
  },
  {
    "id": "Billboard100",
    "name": "Billboard Hot 100",
    "description": "Levels using songs that you would hear on the radio.",
    "levels": [48353992, 122055301, 87481937, 112412828, 81148582],
    "tier": "silver"
  },
  {
    "id": "IDP",
    "name": "Insane Demon Pack I",
    "description": "The easiest insane demons on the list.",
    "levels": [10288836, 814678, 21952243],
    "tier": "copper"
  },
  {
    "id": "IDPII",
    "name": "Insane Demon Pack II",
    "description": "The harder insane demons on the list.",
    "levels": [79428382, 77396433, 83431859],
    "tier": "copper"
  },
  {
    "id": "UED",
    "name": "Unrated Demon Pack",
    "description": "The unrated levels on the list.",
    "levels": [122055301, 124834378, 117939687, 78421544, 145210597],
    "tier": "silver"
  },
  {
    "id": "IP1",
    "name": "Iconic Pack I",
    "description": "Very iconic levels for various reasons.",
    "levels": [814678, 61079355, 3979721],
    "tier": "copper"
  },
  {
    "id": "IP2",
    "name": "Iconic Pack II",
    "description": "Even more iconic levels for various reasons.",
    "levels": [16023141, 10565740, 23262780],
    "tier": "silver"
  },
  {
    "id": "IP3",
    "name": "Iconic Pack III",
    "description": "Harder iconic levels for various reasons.",
    "levels": [35448603, 34057654, 27122654],
    "tier": "gold"
  },
  {
    "id": "IP4",
    "name": "Iconic Pack IV",
    "description": "Even harder iconic levels for various reasons.",
    "levels": [38754426, 26681070, 64658786],
    "tier": "platinum"
  },
  {
    "id": "IP5",
    "name": "Iconic Pack V",
    "description": "You get the point.",
    "levels": [42584142, 52374843, 59075347],
    "tier": "diamond"
  },
  {
    "id": "NC1",
    "name": "Nine Circles Pack I",
    "description": "Levels using the Nine Circles theme.",
    "levels": [112515547, 8147005, 38765979, 55385816],
    "tier": "silver"
  },
  {
    "id": "NC2",
    "name": "Nine Circles Pack II",
    "description": "Harder levels using the Nine Circles theme.",
    "levels": [26681070, 42117203, 52919433, 76159410],
    "tier": "platinum"
  },
  {
    "id": "Default1",
    "name": "Default Songs Pack I",
    "description": "Levels using default songs.",
    "levels": [2374518, 814678, 48765988, 20077821, 105290756],
    "tier": "copper"
  },
  {
    "id": "Default2",
    "name": "Default Songs Pack II",
    "description": "More levels using default songs.",
    "levels": [35579890, 17711004, 23579781, 22259203, 38235367],
    "tier": "gold"
  },
  {
    "id": "Default3",
    "name": "Default Songs Pack III",
    "description": "Even more levels using default songs.",
    "levels": [85383554, 33498127, 59075347],
    "tier": "diamond"
  },
  {
    "id": "Cog",
    "name": "Cognition & Co",
    "description": "Levels using the cognition style",
    "levels": [71025973, 57600307, 64148732],
    "tier": "diamond"
  },
  {
    "id": "60hz",
    "name": "Verified on 60hz",
    "description": "Levels that were verified for the JDL on 60hz.",
    "levels": [58825144, 34057654, 55224007],
    "tier": "gold"
  },
  {
    "id": "RGB",
    "name": "The RGB",
    "description": "The RGB Trilogy.",
    "levels": [31462941, 28220417, 26681070],
    "tier": "platinum"
  },
  {
    "id": "Boss",
    "name": "Bossfight Pack",
    "description": "Levels that feature Bossfights",
    "levels": [60603962, 56703691, 23579781],
    "tier": "platinum"
  },
  {
    "id": "Tylr",
    "name": "Tylr-Sized Pack",
    "description": "The 5 shortest levels on the list.",
    "levels": [82172844, 80966089, 84507862, 145210597, 138356396],
    "tier": "diamond"
  },
  {
    "id": "Zovori",
    "name": "Zovori-Sized Pack",
    "description": "The 5 longest levels on the list.",
    "levels": [45239692, 69010770, 48353992, 48175126, 59933468],
    "tier": "silver"
  },
  {
    "id": "Anatomy",
    "name": "Anatomy Pack",
    "description": "Levels with theming surrounding the human body.",
    "levels": [75248070, 20321297, 123853954],
    "tier": "platinum"
  },
  {
    "id": "Solar",
    "name": "Solar System Pack",
    "description": "Levels that are named after celestial bodies or features in our solar system.",
    "levels": [88943354, 80177488, 19759411, 125025200],
    "tier": "silver"
  },
  {
    "id": "Space",
    "name": "Space Pack",
    "description": "Levels that are themed or named around space in some way.",
    "levels": [76159410, 116401475, 112371654],
    "tier": "platinum"
  },
  {
    "id": "First",
    "name": "Unique First Extremes Pack",
    "description": "Unique levels that Jerbless members beat as their first extreme.",
    "levels": [25241513, 55184818, 35579890],
    "tier": "silver"
  },
  {
    "id": "Old",
    "name": "OG Pack (Beanie)",
    "description": "The 5 oldest completions on the JDL (From Beanie).",
    "levels": [10288836, 814678, 21952243, 25241513, 20761188],
    "tier": "copper"
  },
  {
    "id": "Oldnobean",
    "name": "OG Pack",
    "description": "The 5 oldest completions on the JDL.",
    "levels": [61079355, 814678, 62214792, 45239692, 10565740],
    "tier": "copper"
  },
  {
    "id": "2.01",
    "name": "2.0 Pack I",
    "description": "Classic 2.0 levels.",
    "levels": [24301797, 18697406, 25449475],
    "tier": "copper"
  },
  {
    "id": "2.02",
    "name": "2.0 Pack II",
    "description": "More classic 2.0 levels.",
    "levels": [30194711, 16023141, 35448603],
    "tier": "silver"
  },
  {
    "id": "2.03",
    "name": "2.0 Pack III",
    "description": "Even more classic 2.0 levels.",
    "levels": [27580467, 34057654, 26133601],
    "tier": "gold"
  },
  {
    "id": "2.04",
    "name": "2.0 Pack IV",
    "description": "Even even more classic 2.0 levels.",
    "levels": [27122654, 28220417, 54953085],
    "tier": "platinum"
  },
  {
    "id": "Memory1",
    "name": "Memory Pack I",
    "description": "Levels with memory based gameplay.",
    "levels": [76196489, 77396433, 109637861, 60284098],
    "tier": "copper"
  },
  {
    "id": "Memory2",
    "name": "Memory Pack II",
    "description": "More levels with memory based gameplay.",
    "levels": [16023141, 15265393, 23579781, 38754426],
    "tier": "gold"
  },
  {
    "id": "TeamN2",
    "name": "TeamN2 Pack",
    "description": "Levels by TeamN2.",
    "levels": [27908448, 16023141, 15265393],
    "tier": "silver"
  },
  {
    "id": "Artificial",
    "name": "Artificial Pack",
    "description": "Levels starting with Artificial.",
    "levels": [87033090, 38550757, 27908448, 27122654],
    "tier": "silver"
  },
  {
    "id": "Riot",
    "name": "Riot Pack",
    "description": "Levels uploaded/hosted by Riot.",
    "levels": [20077821, 10565740, 38235367, 59075347],
    "tier": "diamond"
  },
  {
    "id": "Jump",
    "name": "Jump Pack",
    "description": "Levels that Jerbless members have jumped to.",
    "levels": [71025973, 57600307, 79997992, 94156085, 58306889],
    "tier": "diamond"
  },
  {
    "id": "Halo",
    "name": "Halo Pack",
    "description": "Levels that have names relating to Halo in some way.",
    "levels": [60130895, 69333212, 59075347],
    "tier": "diamond"
  },
  {
    "id": "Ant",
    "name": "The Ant Pack",
    "description": "Levels that are associated to Ant in Jerbless.",
    "levels": [62214792, 71025973, 27690100],
    "tier": "diamond"
  },
  {
    "id": "top1i",
    "name": "Top 1 Pack I",
    "description": "Levels that were once top 1.",
    "levels": [26133601, 27122654, 10565740],
    "tier": "gold"
  },
  {
    "id": "top1ii",
    "name": "Top 1 Pack II",
    "description": "Levels that were once top 1.",
    "levels": [42584142, 26681070, 27690100],
    "tier": "diamond"
  },
  {
    "id": "202512DOC",
    "name": "2025 12DOC",
    "description": "Levels that were done as part of the Jerbless 12 Demons of Christmas 2025.",
    "levels": [123853954, 54953085, 58306889, 23262780, 127135884, 112412828, 69010770],
    "tier": "diamond"
  },
  {
    "id": "Nerfd",
    "name": "Supernerfed Pack",
    "description": "Levels that were heavily nerfed from their original state.",
    "levels": [20761188, 54588072, 35448603, 28220417, 52374843],
    "tier": "diamond"
  },
  {
    "id": "anime",
    "name": "Anime Pack",
    "description": "Levels that use songs that are used in anime.",
    "levels": [87425029, 77396433, 83431859],
    "tier": "copper"
  }
]
